weatherwhisper/__init__.py
weatherwhisper/api.py
weatherwhisper/cli.py
weatherwhisper/config.py
weatherwhisper/formatter.py
weatherwhisper-2.0.0.dist-info/licenses/LICENSE
weatherwhisper-2.0.0.dist-info/METADATA
weatherwhisper-2.0.0.dist-info/WHEEL
weatherwhisper-2.0.0.dist-info/entry_points.txt
weatherwhisper-2.0.0.dist-info/top_level.txt
weatherwhisper-2.0.0.dist-info/RECORD
