Metadata-Version: 2.4
Name: weatherwhisper
Version: 2.0.0
Summary: A command-line tool for fetching and displaying weather information
Author: Danush Gopinath
Author-email: danushgopinath8502@gmail.com
Project-URL: Homepage, https://github.com/danushgopinath/weatherwhisper
Project-URL: Bug Tracker, https://github.com/danushgopinath/weatherwhisper/issues
Keywords: weather,cli,openweathermap,forecast,terminal
Classifier: Development Status :: 3 - Alpha
Classifier: Intended Audience :: End Users/Desktop
Classifier: License :: OSI Approved :: MIT License
Classifier: Programming Language :: Python :: 3
Classifier: Programming Language :: Python :: 3.6
Classifier: Programming Language :: Python :: 3.7
Classifier: Programming Language :: Python :: 3.8
Classifier: Programming Language :: Python :: 3.9
Requires-Python: >=3.6
License-File: LICENSE
Requires-Dist: click
Requires-Dist: requests
Requires-Dist: colorama
Requires-Dist: tabulate
Requires-Dist: configparser
Dynamic: author
Dynamic: author-email
Dynamic: classifier
Dynamic: description
Dynamic: description-content-type
Dynamic: keywords
Dynamic: license-file
Dynamic: project-url
Dynamic: requires-dist
Dynamic: requires-python
Dynamic: summary
